{
  "project_info": {
    "project_number": "748643708301",
    "project_id": "certain-gearbox-476003-c7",
    "storage_bucket": "certain-gearbox-476003-c7.appspot.com"
  },
  "client": [
    {
      "client_info": {
        "mobilesdk_app_id": "1:748643708301:android:kanjilearningplaceholder",
        "android_client_info": {
          "package_name": "com.example.kanjilearning"
        }
      },
      "oauth_client": [
        {
          "client_id": "748643708301-90fr170bgq8s0ienon6hg4cg9dnnui2b.apps.googleusercontent.com",
          "client_type": 3
        }
      ],
      "api_key": [
        {
          "current_key": "AIzaSyD-PLACEHOLDER"
        }
      ],
      "services": {
        "appinvite_service": {
          "other_platform_oauth_client": []
        }
      }
    }
  ],
  "configuration_version": "1"
}
